[
  {
    "inputs": [],
    "stateMutability": "nonpayable",
    "type": "constructor"
  },
  {
    "inputs": [
      {
        "internalType": "address",
        "name": "owner",
        "type": "address"
      }
    ],
    "name": "OwnableInvalidOwner",
    "type": "error"
  },
  {
    "inputs": [
      {
        "internalType": "address",
        "name": "account",
        "type": "address"
      }
    ],
    "name": "OwnableUnauthorizedAccount",
    "type": "error"
  },
  {
    "anonymous": false,
    "inputs": [
      {
        "indexed": true,
        "internalType": "address",
        "name": "previousOwner",
        "type": "address"
      },
      {
        "indexed": true,
        "internalType": "address",
        "name": "newOwner",
        "type": "address"
      }
    ],
    "name": "OwnershipTransferred",
    "type": "event"
  },
  {
    "anonymous": false,
    "inputs": [
      {
        "indexed": true,
        "internalType": "uint256",
        "name": "requestId",
        "type": "uint256"
      }
    ],
    "name": "RequestExpired",
    "type": "event"
  },
  {
    "anonymous": false,
    "inputs": [
      {
        "indexed": true,
        "internalType": "uint256",
        "name": "requestId",
        "type": "uint256"
      },
      {
        "indexed": true,
        "internalType": "address",
        "name": "requester",
        "type": "address"
      },
      {
        "indexed": true,
        "internalType": "address",
        "name": "nftContract",
        "type": "address"
      },
      {
        "indexed": false,
        "internalType": "bytes",
        "name": "encryptedPayload",
        "type": "bytes"
      }
    ],
    "name": "RequestSubmitted",
    "type": "event"
  },
  {
    "anonymous": false,
    "inputs": [
      {
        "indexed": true,
        "internalType": "uint256",
        "name": "requestId",
        "type": "uint256"
      },
      {
        "indexed": false,
        "internalType": "uint8",
        "name": "status",
        "type": "uint8"
      },
      {
        "indexed": false,
        "internalType": "bytes",
        "name": "encryptedPayload",
        "type": "bytes"
      }
    ],
    "name": "ResponseSubmitted",
    "type": "event"
  },
  {
    "inputs": [],
    "name": "_activeCount",
    "outputs": [
      {
        "internalType": "uint256",
        "name": "",
        "type": "uint256"
      }
    ],
    "stateMutability": "view",
    "type": "function"
  },
  {
    "inputs": [],
    "name": "_pendingCount",
    "outputs": [
      {
        "internalType": "uint256",
        "name": "",
        "type": "uint256"
      }
    ],
    "stateMutability": "view",
    "type": "function"
  },
  {
    "inputs": [],
    "name": "getAvailableCapacity",
    "outputs": [
      {
        "internalType": "uint256",
        "name": "",
        "type": "uint256"
      }
    ],
    "stateMutability": "view",
    "type": "function"
  },
  {
    "inputs": [
      {
        "internalType": "uint256",
        "name": "requestId",
        "type": "uint256"
      }
    ],
    "name": "getRequest",
    "outputs": [
      {
        "components": [
          {
            "internalType": "uint256",
            "name": "id",
            "type": "uint256"
          },
          {
            "internalType": "address",
            "name": "requester",
            "type": "address"
          },
          {
            "internalType": "address",
            "name": "nftContract",
            "type": "address"
          },
          {
            "internalType": "bytes",
            "name": "encryptedPayload",
            "type": "bytes"
          },
          {
            "internalType": "uint8",
            "name": "status",
            "type": "uint8"
          },
          {
            "internalType": "bytes",
            "name": "responsePayload",
            "type": "bytes"
          },
          {
            "internalType": "uint256",
            "name": "submittedAt",
            "type": "uint256"
          },
          {
            "internalType": "uint256",
            "name": "respondedAt",
            "type": "uint256"
          }
        ],
        "internalType": "struct BrokerRequests.Request",
        "name": "request",
        "type": "tuple"
      }
    ],
    "stateMutability": "view",
    "type": "function"
  },
  {
    "inputs": [],
    "name": "getRequestCount",
    "outputs": [
      {
        "internalType": "uint256",
        "name": "count",
        "type": "uint256"
      }
    ],
    "stateMutability": "view",
    "type": "function"
  },
  {
    "inputs": [
      {
        "internalType": "uint256[]",
        "name": "requestIds",
        "type": "uint256[]"
      }
    ],
    "name": "markExpired",
    "outputs": [],
    "stateMutability": "nonpayable",
    "type": "function"
  },
  {
    "inputs": [
      {
        "internalType": "address",
        "name": "",
        "type": "address"
      }
    ],
    "name": "nftContractToRequestId",
    "outputs": [
      {
        "internalType": "uint256",
        "name": "",
        "type": "uint256"
      }
    ],
    "stateMutability": "view",
    "type": "function"
  },
  {
    "inputs": [],
    "name": "owner",
    "outputs": [
      {
        "internalType": "address",
        "name": "",
        "type": "address"
      }
    ],
    "stateMutability": "view",
    "type": "function"
  },
  {
    "inputs": [
      {
        "internalType": "address",
        "name": "nftContract",
        "type": "address"
      }
    ],
    "name": "releaseAllocation",
    "outputs": [],
    "stateMutability": "nonpayable",
    "type": "function"
  },
  {
    "inputs": [],
    "name": "renounceOwnership",
    "outputs": [],
    "stateMutability": "nonpayable",
    "type": "function"
  },
  {
    "inputs": [],
    "name": "requestExpirationTime",
    "outputs": [
      {
        "internalType": "uint256",
        "name": "",
        "type": "uint256"
      }
    ],
    "stateMutability": "view",
    "type": "function"
  },
  {
    "inputs": [
      {
        "internalType": "uint256",
        "name": "",
        "type": "uint256"
      }
    ],
    "name": "requests",
    "outputs": [
      {
        "internalType": "uint256",
        "name": "id",
        "type": "uint256"
      },
      {
        "internalType": "address",
        "name": "requester",
        "type": "address"
      },
      {
        "internalType": "address",
        "name": "nftContract",
        "type": "address"
      },
      {
        "internalType": "bytes",
        "name": "encryptedPayload",
        "type": "bytes"
      },
      {
        "internalType": "uint8",
        "name": "status",
        "type": "uint8"
      },
      {
        "internalType": "bytes",
        "name": "responsePayload",
        "type": "bytes"
      },
      {
        "internalType": "uint256",
        "name": "submittedAt",
        "type": "uint256"
      },
      {
        "internalType": "uint256",
        "name": "respondedAt",
        "type": "uint256"
      }
    ],
    "stateMutability": "view",
    "type": "function"
  },
  {
    "inputs": [
      {
        "internalType": "address",
        "name": "",
        "type": "address"
      },
      {
        "internalType": "uint256",
        "name": "",
        "type": "uint256"
      }
    ],
    "name": "requesterToRequestIds",
    "outputs": [
      {
        "internalType": "uint256",
        "name": "",
        "type": "uint256"
      }
    ],
    "stateMutability": "view",
    "type": "function"
  },
  {
    "inputs": [
      {
        "internalType": "uint256",
        "name": "newExpirationTime",
        "type": "uint256"
      }
    ],
    "name": "setRequestExpirationTime",
    "outputs": [],
    "stateMutability": "nonpayable",
    "type": "function"
  },
  {
    "inputs": [
      {
        "internalType": "uint256",
        "name": "_totalCapacity",
        "type": "uint256"
      }
    ],
    "name": "setTotalCapacity",
    "outputs": [],
    "stateMutability": "nonpayable",
    "type": "function"
  },
  {
    "inputs": [
      {
        "internalType": "address",
        "name": "nftContract",
        "type": "address"
      },
      {
        "internalType": "bytes",
        "name": "encryptedPayload",
        "type": "bytes"
      }
    ],
    "name": "submitRequest",
    "outputs": [
      {
        "internalType": "uint256",
        "name": "requestId",
        "type": "uint256"
      }
    ],
    "stateMutability": "nonpayable",
    "type": "function"
  },
  {
    "inputs": [
      {
        "internalType": "uint256",
        "name": "requestId",
        "type": "uint256"
      },
      {
        "internalType": "bytes",
        "name": "encryptedPayload",
        "type": "bytes"
      }
    ],
    "name": "submitResponse",
    "outputs": [],
    "stateMutability": "nonpayable",
    "type": "function"
  },
  {
    "inputs": [],
    "name": "totalCapacity",
    "outputs": [
      {
        "internalType": "uint256",
        "name": "",
        "type": "uint256"
      }
    ],
    "stateMutability": "view",
    "type": "function"
  },
  {
    "inputs": [
      {
        "internalType": "address",
        "name": "newOwner",
        "type": "address"
      }
    ],
    "name": "transferOwnership",
    "outputs": [],
    "stateMutability": "nonpayable",
    "type": "function"
  }
]
